LICENSE.md
README.md
setup.py
osmo_trade/__init__.py
osmo_trade/config_data.py
osmo_trade/constants.py
osmo_trade/data_feed.py
osmo_trade/transaction_build.py
osmo_trade/wallet.py
osmo_trade.egg-info/PKG-INFO
osmo_trade.egg-info/SOURCES.txt
osmo_trade.egg-info/dependency_links.txt
osmo_trade.egg-info/top_level.txt
osmo_trade/_pools/__init__.py
osmo_trade/_pools/pools.py