Metadata-Version: 2.1
Name: osmo-trade
Version: 0.1.1
Summary: SDK to trade on osmosis DEX
Home-page: https://github.com/0xmercury/osmo_trade
Author: 0xmercury
Author-email: osmocosmo2@gmail.com
License: Apache License 2.0
Project-URL: Source, https://github.com/0xmercury/osmo_trade
Classifier: Intended Audience :: Developers
Classifier: License :: OSI Approved :: Apache Software License
Classifier: Operating System :: OS Independent
Classifier: Programming Language :: Python :: 3.9
License-File: LICENSE.md
